htmlhexviewer/__init__.py
htmlhexviewer/__main__.py
htmlhexviewer/templates/base.html
htmlhexviewer/templates/script.js
htmlhexviewer/templates/style.css
HTMLHexViewer-0.1.2.dist-info/LICENSE
HTMLHexViewer-0.1.2.dist-info/METADATA
HTMLHexViewer-0.1.2.dist-info/WHEEL
HTMLHexViewer-0.1.2.dist-info/entry_points.txt
HTMLHexViewer-0.1.2.dist-info/top_level.txt
HTMLHexViewer-0.1.2.dist-info/RECORD
